drf_standardized_errors/__init__.py
drf_standardized_errors/apps.py
drf_standardized_errors/formatter.py
drf_standardized_errors/handler.py
drf_standardized_errors/openapi.py
drf_standardized_errors/openapi_hooks.py
drf_standardized_errors/openapi_serializers.py
drf_standardized_errors/openapi_utils.py
drf_standardized_errors/openapi_validation_errors.py
drf_standardized_errors/py.typed
drf_standardized_errors/settings.py
drf_standardized_errors/types.py
drf_standardized_errors-0.13.0.dist-info/LICENSE
drf_standardized_errors-0.13.0.dist-info/WHEEL
drf_standardized_errors-0.13.0.dist-info/METADATA
drf_standardized_errors-0.13.0.dist-info/RECORD
