Metadata-Version: 2.1
Name: drf-standardized-errors
Version: 0.13.0
Summary: Standardize your API error responses.
Keywords: standardized errors,errors formatter,django rest framework,exception handler
Author: Ghazi Abbassi
Requires-Python: >=3.8
Classifier: Intended Audience :: Developers
Classifier: License :: OSI Approved :: MIT License
Classifier: Programming Language :: Python :: 3
Classifier: Programming Language :: Python :: 3.8
Classifier: Programming Language :: Python :: 3.9
Classifier: Programming Language :: Python :: 3.10
Classifier: Programming Language :: Python :: 3.11
Classifier: Programming Language :: Python :: 3.12
Requires-Dist: django >=3.2
Requires-Dist: djangorestframework >=3.12
Requires-Dist: pre-commit ; extra == "dev"
Requires-Dist: sphinx!=5.2.0.post0 ; extra == "doc"
Requires-Dist: sphinx-autobuild ; extra == "doc"
Requires-Dist: sphinx-rtd-theme>=1.1.0 ; extra == "doc"
Requires-Dist: myst-parser ; extra == "doc"
Requires-Dist: drf-spectacular ; extra == "openapi"
Requires-Dist: inflection ; extra == "openapi"
Requires-Dist: flit ; extra == "release"
Requires-Dist: keyring ; extra == "release"
Requires-Dist: tbump ; extra == "release"
Requires-Dist: tox ; extra == "test"
Requires-Dist: tox-gh-actions ; extra == "test"
Project-URL: Changelog, https://github.com/ghazi-git/drf-standardized-errors/releases
Project-URL: Code, https://github.com/ghazi-git/drf-standardized-errors
Project-URL: Documentation, https://drf-standardized-errors.readthedocs.io/en/latest/
Project-URL: Homepage, https://github.com/ghazi-git/drf-standardized-errors
Project-URL: Issues, https://github.com/ghazi-git/drf-standardized-errors/issues
Provides-Extra: dev
Provides-Extra: doc
Provides-Extra: openapi
Provides-Extra: release
Provides-Extra: test
